src/arrow.sv
`timescale 1ns / 1ps
`default_nettype none

module arrow #(parameter WIDTH = 8,HEIGHT = 32)(
	input wire clk,
	input wire rst,
	input wire[10:0] hcount_in,
	input wire[9:0] vcount_in,
	input wire valid_in,
	input wire[2:0] speed_in,
	input wire[1:0] direction_in,
	input wire inversed_in,

	output logic[11:0] pixel_out,
	output logic valid_out
);

logic[10:0] x;
logic[9:0] y;
logic old_valid_in;
logic valid_out_buffer;
always_ff @(posedge clk)begin
	/*if(rst)begin
		pixel_out <= 0;
		valid_out <= 0;
	end
	else begin*/
		if(~old_valid_in && valid_in)begin
                	case(direction_in)
                        	2'b00:begin
                                	x <= 512;
                                	y <= 0;
                        	end
                        	2'b01:begin
                                	x <= 512;
                                	y <= 720;
                        	end
                        	2'b10:begin
                                	x <= 0;
                                	y <= 384;
                        	end
                        	2'b11:begin
                                	x <= 512;
                                	y <= 0;
                        	end
                	endcase
        	end else if(old_valid_in && valid_in)begin
                	if(hcount_in == 0 && vcount_in == 0)begin
                        	case(direction_in)
                                	2'b00:begin
                                        	y <= y + 4;
                               	 	end
                                	2'b01:begin
                                        	y <= y - 4;
                                	end
                                	2'b10:begin
                                        	x <= x + 4;
                                	end
                                	2'b11:begin
                                        	y <= y + 4;
                                	end
                        	endcase
                	end
		end
	//end
	//valid_out = valid_in ? /*(hcount_in >= x) && (hcount_in <= x+WIDTH) && (vcount_in >= y) && (vcount_in <= y+HEIGHT)*//*1 : 0;
	//valid_out = (hcount_in >= x) && (hcount_in <= x+WIDTH) && (vcount_in >= y) && (vcount_in <= y+HEIGHT);
	//pixel_out = valid_out ? 12'hF00 : 0;
	old_valid_in <= valid_in;
end
assign valid_out = valid_in ? ((hcount_in >= x) && (hcount_in <= x+WIDTH) && (vcount_in >= y) && (vcount_in <= y+HEIGHT)) : 0;
/*always_comb begin
	valid_out_buffer = (hcount_in >= x) && (hcount_in <= x+WIDTH) && (vcount_in >= y) && (vcount_in <= y+HEIGHT);
end*/
//assign valid_out = (hcount_in >= x) && (hcount_in <= x+WIDTH) && (vcount_in >= y) && (vcount_in <= y+HEIGHT);
//assign valid_out = valid_out_buffer;
assign pixel_out = valid_out ? 12'hF00 : 0;
endmodule
`default_nettype wire

sim/arrow_tb.sv
`default_nettype none
`timescale 1ns / 1ps
module arrow_tb;

logic clk;
logic rst;
logic [10:0] hcount_in;
logic [9:0] vcount_in;
logic  valid_in;
logic[2:0] speed_in;
logic[1:0] direction_in;
logic inversed_in;

logic[11:0] pixel_out;
logic valid_out;

arrow uut(
	.clk(clk),
	.rst(rst),
	.hcount_in(hcount_in),
	.vcount_in(vcount_in),
	.valid_in(valid_in),
	.speed_in(speed_in),
	.direction_in(direction_in),
	.inversed_in(inversed_in),
	.pixel_out(pixel_out),
	.valid_out(valid_out)
);

always begin
        #10;
        clk = !clk;
end

initial begin
        $display("Starting Sim");
        $dumpfile("arrow.vcd");
        $dumpvars(0,arrow_tb);
        rst = 1;
        clk = 0;
        #20;
        rst = 0;
        for(int i = 0;i<30;i++)begin
                hcount_in = 0;
                vcount_in = 0;
		valid_in = 0;
		direction_in = 2'b00;
		inversed_in = 0;
		speed_in = 0;
                #20;
        end
	valid_in <= 1;
        #200;
	valid_in <= 0;
	#1000;
        $display("Finishing Sim");
        $finish;
end



endmodule
`default_nettype wire

arrow.vcd
$date
	Tue Nov 15 13:03:30 2022
$end
$version
	Icarus Verilog
$end
$timescale
	1ps
$end
$scope module arrow_tb $end
$var wire 1 ! valid_out $end
$var wire 12 " pixel_out [11:0] $end
$var reg 1 # clk $end
$var reg 2 $ direction_in [1:0] $end
$var reg 11 % hcount_in [10:0] $end
$var reg 1 & inversed_in $end
$var reg 1 ' rst $end
$var reg 3 ( speed_in [2:0] $end
$var reg 1 ) valid_in $end
$var reg 10 * vcount_in [9:0] $end
$scope module uut $end
$var wire 1 # clk $end
$var wire 2 + direction_in [1:0] $end
$var wire 11 , hcount_in [10:0] $end
$var wire 1 & inversed_in $end
$var wire 1 ' rst $end
$var wire 3 - speed_in [2:0] $end
$var wire 1 ) valid_in $end
$var wire 10 . vcount_in [9:0] $end
$var reg 1 / old_valid_in $end
$var reg 12 0 pixel_out [11:0] $end
$var reg 1 ! valid_out $end
$var reg 11 1 x [10:0] $end
$var reg 10 2 y [9:0] $end
$upscope $end
$scope begin $ivl_for_loop0 $end
$var integer 32 3 i [31:0] $end
$upscope $end
$upscope $end
$enddefinitions $end
#0
$dumpvars
b0 3
bx 2
bx 1
bx 0
x/
bx .
bx -
bx ,
bx +
bx *
x)
bx (
1'
x&
bx %
bx $
0#
bx "
x!
$end
#10000
0!
b0 "
b0 0
1#
#20000
0#
b0 (
b0 -
0&
b0 $
b0 +
0)
b0 *
b0 .
b0 %
b0 ,
0'
#30000
0/
bx00000000 "
bx00000000 0
x!
1#
#40000
0#
b1 3
#50000
1#
#60000
0#
b10 3
#70000
1#
#80000
0#
b11 3
#90000
1#
#100000
0#
b100 3
#110000
1#
#120000
0#
b101 3
#130000
1#
#140000
0#
b110 3
#150000
1#
#160000
0#
b111 3
#170000
1#
#180000
0#
b1000 3
#190000
1#
#200000
0#
b1001 3
#210000
1#
#220000
0#
b1010 3
#230000
1#
#240000
0#
b1011 3
#250000
1#
#260000
0#
b1100 3
#270000
1#
#280000
0#
b1101 3
#290000
1#
#300000
0#
b1110 3
#310000
1#
#320000
0#
b1111 3
#330000
1#
#340000
0#
b10000 3
#350000
1#
#360000
0#
b10001 3
#370000
1#
#380000
0#
b10010 3
#390000
1#
#400000
0#
b10011 3
#410000
1#
#420000
0#
b10100 3
#430000
1#
#440000
0#
b10101 3
#450000
1#
#460000
0#
b10110 3
#470000
1#
#480000
0#
b10111 3
#490000
1#
#500000
0#
b11000 3
#510000
1#
#520000
0#
b11001 3
#530000
1#
#540000
0#
b11010 3
#550000
1#
#560000
0#
b11011 3
#570000
1#
#580000
0#
b11100 3
#590000
1#
#600000
0#
b11101 3
#610000
1#
#620000
1)
0#
b11110 3
#630000
1/
b0 2
b1000000000 1
1#
#640000
0#
#650000
b100 2
b0 "
b0 0
0!
1#
#660000
0#
#670000
b1000 2
1#
#680000
0#
#690000
b1100 2
1#
#700000
0#
#710000
b10000 2
1#
#720000
0#
#730000
b10100 2
1#
#740000
0#
#750000
b11000 2
1#
#760000
0#
#770000
b11100 2
1#
#780000
0#
#790000
b100000 2
1#
#800000
0#
#810000
b100100 2
1#
#820000
0)
0#
#830000
0/
1#
