src/block_sprite.sv
module block_sprite #(
  parameter WIDTH=256, HEIGHT=256,X_FIXED = 128,Y_FIXED = 128, COLOR=12'hFFF)(
  input wire is_fixed,
  input wire [10:0] x_in, hcount_in,
  input wire [9:0]  y_in, vcount_in,
  output logic [11:0] pixel_out,
  output logic in_sprite);

  logic in_sprite_buffer;
  always_comb begin
	  if(~is_fixed)begin
		  in_sprite_buffer = ((hcount_in >= x_in && hcount_in < (x_in + WIDTH)) && (vcount_in >= y_in && vcount_in < (y_in + HEIGHT)));
	  end else begin
		  in_sprite_buffer = ((hcount_in >= X_FIXED && hcount_in < (X_FIXED + WIDTH)) && (vcount_in >= Y_FIXED && vcount_in < (Y_FIXED + HEIGHT)));
	  end
  end


  assign pixel_out = in_sprite ? COLOR : 0;
  assign in_sprite = in_sprite_buffer;
endmodule

src/arrow.sv
`timescale 1ns / 1ps
`default_nettype none

module arrow #(parameter WIDTH = 8,HEIGHT = 32)(
	input wire clk,
	input wire rst,
	input wire[10:0] hcount_in,
	input wire[9:0] vcount_in,
	input wire valid_in,
	input wire[2:0] speed_in,
	input wire[1:0] direction_in,
	input wire inversed_in,

	output logic[11:0] pixel_out,
	output logic valid_out
);

logic[10:0] x;
logic[9:0] y;
logic old_valid_in;
logic valid_out_buffer;
always_ff @(posedge clk)begin
	/*if(rst)begin
		pixel_out <= 0;
		valid_out <= 0;
	end
	else begin*/
		if(~old_valid_in && valid_in)begin
                	case(direction_in)
                        	2'b00:begin
                                	x <= 512;
                                	y <= 0;
                        	end
                        	2'b01:begin
                                	x <= 512;
                                	y <= 720;
                        	end
                        	2'b10:begin
                                	x <= 0;
                                	y <= 384;
                        	end
                        	2'b11:begin
                                	x <= 512;
                                	y <= 0;
                        	end
                	endcase
        	end else if(old_valid_in && valid_in)begin
                	if(hcount_in == 0 && vcount_in == 0)begin
                        	case(direction_in)
                                	2'b00:begin
                                        	y <= y + 4;
                               	 	end
                                	2'b01:begin
                                        	y <= y - 4;
                                	end
                                	2'b10:begin
                                        	x <= x + 4;
                                	end
                                	2'b11:begin
                                        	y <= y + 4;
                                	end
                        	endcase
                	end
		end
	//end
	//valid_out = valid_in ? /*(hcount_in >= x) && (hcount_in <= x+WIDTH) && (vcount_in >= y) && (vcount_in <= y+HEIGHT)*//*1 : 0;
	//valid_out = (hcount_in >= x) && (hcount_in <= x+WIDTH) && (vcount_in >= y) && (vcount_in <= y+HEIGHT);
	//pixel_out = valid_out ? 12'hF00 : 0;
	old_valid_in <= valid_in;
end
assign valid_out = valid_in ? ((hcount_in >= x) && (hcount_in <= x+WIDTH) && (vcount_in >= y) && (vcount_in <= y+HEIGHT)) : 0;
/*always_comb begin
	valid_out_buffer = (hcount_in >= x) && (hcount_in <= x+WIDTH) && (vcount_in >= y) && (vcount_in <= y+HEIGHT);
end*/
//assign valid_out = (hcount_in >= x) && (hcount_in <= x+WIDTH) && (vcount_in >= y) && (vcount_in <= y+HEIGHT);
//assign valid_out = valid_out_buffer;
assign pixel_out = valid_out ? 12'hF00 : 0;
endmodule
`default_nettype wire

src/shield.sv
`default_nettype none
`timescale 1ns / 1ps
module shield(
	input wire[10:0] hcount_in,
	input wire[9:0] vcount_in,
	input wire[1:0] rotate_in,

	output logic[11:0] pixel_out
);

logic[10:0] x,width;
logic[9:0] y,height;
always_comb begin
	case(rotate_in)
		2'b00:begin
			x = 448;
			y = 320;
			width = 128;
			height = 4;
		end
		2'b11:begin
			x = 448;
			y = 320;
			width = 4;
			height = 128;
		end
		2'b10:begin
			x = 568;
			y = 320;
			width = 4;
			height = 128;
		end
		2'b01:begin
			x = 448;
			y = 440;
			width = 128;
			height = 4;
		end
	endcase
end
logic in_sprite;
assign in_sprite = (hcount_in >= x) && (hcount_in <= x+width)  && ((vcount_in >= y) && (vcount_in <= y+height));
assign pixel_out = in_sprite ? 12'hFFF : 0;
endmodule
`default_nettype wire

src/enemy.sv
`default_nettype none
`timescale 1ns / 1ps

module enemy(
	input wire clk,
	input wire rst,
	input wire[10:0] hcount_in, //hcount
	input wire[9:0] vcount_in, //vcount
	input wire[3:0] state_in, //used to check if this module is busy
	input wire[3:0] turn_in, //to determine which pattern to adapt
	input wire[1:0] rotate_in, //input from camera interaction

	output logic busy_out, //busy while this is high
	output logic finished_out, //asserted high for one clk cycle when the module exits busy state
	output logic[11:0] pixel_out //pixel output
);
logic busy_out_buffer;

//shield
logic[11:0] shield_out;
shield player_shield(.hcount_in(hcount_in),.vcount_in(vcount_in),.rotate_in(2'b00),.pixel_out(shield_out));

logic[9:0] timings[71:0];
logic[9:0] speeds[71:0];
logic[9:0] directions[47:0];
logic[9:0] inverseds[23:0];
//patterns
//pattern #(72'h249_249_249_249_249_249,72'h249_249_249_249_249_249,48'h0,24'h0,0) pattern1(.turn_in(turn_in),.valid_out(1),.timing(timings[0]),.speed(speeds[0]),.direction(directions[0]),.inversed(inverseds[0]));

assign timings[0] = 72'h249_249_249_249_249_249;
//logic[23:0] arrow_on;
//24 arrows
logic[23:0] arrow_valid_in;
//logic[11:0][23:0] arrow_out;
logic[23:0] arrow_out[11:0];
logic[23:0] arrow_valid_out;
arrow #(8,32) arrow1(.clk(clk),.rst(rst),.hcount_in(hcount_in),.vcount_in(vcount_in),.valid_in(arrow_valid_in[0]),.speed_in(0),.direction_in(2'b00),.inversed_in(0),.pixel_out(/*arrow_out[0]*/arrow_out_1),.valid_out(/*arrow_valid_out[0])*/arrow_valid_1));
arrow #(8,32) arrow2(.clk(clk),.rst(rst),.hcount_in(hcount_in),.vcount_in(vcount_in),.valid_in(arrow_valid_in[1]),.speed_in(0),.direction_in(2'b01),.inversed_in(0),.pixel_out(/*arrow_out[1]*/arrow_out_2),.valid_out(/*arrow_valid_out[1])*/arrow_valid_2));
arrow #(8,32) arrow3(.clk(clk),.rst(rst),.hcount_in(hcount_in),.vcount_in(vcount_in),.valid_in(arrow_valid_in[2]),.speed_in(0),.direction_in(2'b10),.inversed_in(0),.pixel_out(/*arrow_out[2]*/arrow_out_3),.valid_out(/*arrow_valid_out[2]*/arrow_valid_3));

//arrow out individual
logic arrow_valid_1,arrow_valid_2,arrow_valid_3;
logic[11:0] arrow_out_1,arrow_out_2,arrow_out_3;

logic frame_top_out,frame_bottom_out,frame_right_out,frame_left_out;
logic[11:0] frame_top_pixel;
logic[11:0] frame_bottom_pixel;
logic[11:0] frame_right_pixel;
logic[11:0] frame_left_pixel;
block_sprite #(160,8,432,304,12'hFFF) frame_top(.is_fixed(1),.x_in(0),.hcount_in(hcount_in),.y_in(0),.vcount_in(vcount_in),.pixel_out(frame_top_pixel),.in_sprite(frame_top_out));
block_sprite #(8,160,432,304,12'hFFF) frame_left(.is_fixed(1),.x_in(0),.hcount_in(hcount_in),.y_in(0),.vcount_in(vcount_in),.in_sprite(frame_left_out),.pixel_out(frame_left_pixel));
block_sprite #(8,160,584,304,12'hFFF) frame_right(.is_fixed(1),.x_in(0),.hcount_in(hcount_in),.y_in(0),.vcount_in(vcount_in),.in_sprite(frame_right_out),.pixel_out(frame_right_pixel));
block_sprite #(160,8,432,456,12'hFFF) frame_bottom(.is_fixed(1),.x_in(0),.hcount_in(hcount_in),.y_in(0),.vcount_in(vcount_in),.in_sprite(frame_bottom_out),.pixel_out(frame_bottom_pixel));

always_comb begin
	if(busy_out_buffer)begin
		/*if(frame_top_out)
                	pixel_out = frame_top_pixel;
        	if(frame_bottom_out)
                	pixel_out = frame_bottom_pixel;
        	if(frame_right_out)
                	pixel_out = frame_right_pixel;
        	if(frame_left_out)
                	pixel_out = frame_left_pixel;*/
		pixel_out = frame_bottom_pixel + frame_top_pixel + frame_left_pixel + frame_right_pixel + arrow_out_1 + arrow_out_2 + arrow_out_3;
		//pixel_out = 1;
	end
end


logic[31:0] timing_count;
logic[6:0] arrow_count_first;
logic[6:0] arrow_count_last;
logic[3:0] old_state_in; //detecting rising edge at the beginning of each phase
always_ff @(posedge clk)begin
	if(rst)begin
		busy_out_buffer <= 0;
		finished_out <= 0;
		timing_count <= 0;
		old_state_in <= 4'b1010;
		arrow_count_first <= 0;
		//pixel_out <= 0;
	end else begin
		if(state_in == 4'b1000 && old_state_in != state_in)begin
			busy_out_buffer <= 1;
			timing_count <= 0;
			//arrow_count_first <= 0;
			arrow_valid_in <= 24'h000000;
		end
		if(busy_out_buffer ==1)begin

			timing_count <= timing_count + 1;
                	if(timing_count == /*timings[0][arrow_count+:3]5*6500000*/timings[0][arrow_count_first+:3]*5*65000000)begin
                        	arrow_valid_in <= {arrow_valid_in[22:0],1'b1};
				arrow_count_first <= arrow_count_first + 3;
                       		timing_count <= 0;
                	end

		end

		//end
		/*if(busy_out_buffer)begin
			if(hcount_in == 0 && vcount_in == 0)begin
				//arrow_valid_in <= 0;
				//arrow_valid_in = 24'h000003;
				timing_count <= timing_count + 1;
				if(timing_count == 10)begin
					timing_count <= 0;
					arrow_valid_in <= 24'h000003;
					//arrow_valid_in[1] <= 0;
				end
			end
		old_state_in <= state_in;
		end*/
	        old_state_in <= state_in;
	end
	//output the pixel value from 24 arrows, heart, etc. 
	//alpha blending
	//interval control
end

assign busy_out = busy_out_buffer;
endmodule
`default_nettype wire

sim/enemy_tb.sv
`default_nettype none
`timescale 1ns / 1ps

module enemy_tb;

logic clk;
logic rst;

logic [10:0] hcount_in;
logic [9:0] vcount_in;
logic [3:0] state_in;
logic [3:0] turn_in;
logic [1:0] rotate_in;

logic busy_out;
logic finished_out;
logic [11:0] pixel_out;
enemy uut(
	.clk(clk),
	.rst(rst),
	.hcount_in(hcount_in),
	.vcount_in(vcount_in),
	.state_in(state_in),
	.turn_in(turn_in),
	.rotate_in(rotate_in),
	.busy_out(busy_out),
	.finished_out(finished_out),
	.pixel_out(pixel_out)
);

always begin
	#10;
       	clk = !clk;
end

initial begin
	$display("Starting Sim");
	$dumpfile("enemy.vcd");
	$dumpvars(0,enemy_tb);
	rst = 1;
	clk = 0;
	#20;
	rst = 0;
	for(int i = 0;i<100;i++)begin
		hcount_in = 513;
		vcount_in = 256;
		state_in = 4'b1000;
		turn_in = 0;
		rotate_in = 2'b0;
		#20;
	end
	#100;
	$display("Finishing Sim");
	$finish;
end


endmodule
`default_nettype wire

enemy.vcd
$date
	Tue Nov 15 13:46:50 2022
$end
$version
	Icarus Verilog
$end
$timescale
	1ps
$end
$scope module enemy_tb $end
$var wire 12 ! pixel_out [11:0] $end
$var wire 1 " finished_out $end
$var wire 1 # busy_out $end
$var reg 1 $ clk $end
$var reg 11 % hcount_in [10:0] $end
$var reg 2 & rotate_in [1:0] $end
$var reg 1 ' rst $end
$var reg 4 ( state_in [3:0] $end
$var reg 4 ) turn_in [3:0] $end
$var reg 10 * vcount_in [9:0] $end
$scope module uut $end
$var wire 1 # busy_out $end
$var wire 1 $ clk $end
$var wire 11 + hcount_in [10:0] $end
$var wire 2 , rotate_in [1:0] $end
$var wire 1 ' rst $end
$var wire 4 - state_in [3:0] $end
$var wire 4 . turn_in [3:0] $end
$var wire 10 / vcount_in [9:0] $end
$var wire 12 0 shield_out [11:0] $end
$var wire 12 1 frame_top_pixel [11:0] $end
$var wire 1 2 frame_top_out $end
$var wire 12 3 frame_right_pixel [11:0] $end
$var wire 1 4 frame_right_out $end
$var wire 12 5 frame_left_pixel [11:0] $end
$var wire 1 6 frame_left_out $end
$var wire 12 7 frame_bottom_pixel [11:0] $end
$var wire 1 8 frame_bottom_out $end
$var wire 1 9 arrow_valid_3 $end
$var wire 1 : arrow_valid_2 $end
$var wire 1 ; arrow_valid_1 $end
$var wire 12 < arrow_out_3 [11:0] $end
$var wire 12 = arrow_out_2 [11:0] $end
$var wire 12 > arrow_out_1 [11:0] $end
$var reg 7 ? arrow_count_first [6:0] $end
$var reg 24 @ arrow_valid_in [23:0] $end
$var reg 1 A busy_out_buffer $end
$var reg 1 " finished_out $end
$var reg 4 B old_state_in [3:0] $end
$var reg 12 C pixel_out [11:0] $end
$var reg 32 D timing_count [31:0] $end
$scope module arrow1 $end
$var wire 1 $ clk $end
$var wire 2 E direction_in [1:0] $end
$var wire 11 F hcount_in [10:0] $end
$var wire 1 G inversed_in $end
$var wire 1 ' rst $end
$var wire 3 H speed_in [2:0] $end
$var wire 1 I valid_in $end
$var wire 10 J vcount_in [9:0] $end
$var wire 1 ; valid_out $end
$var wire 12 K pixel_out [11:0] $end
$var reg 1 L old_valid_in $end
$var reg 11 M x [10:0] $end
$var reg 10 N y [9:0] $end
$upscope $end
$scope module arrow2 $end
$var wire 1 $ clk $end
$var wire 2 O direction_in [1:0] $end
$var wire 11 P hcount_in [10:0] $end
$var wire 1 Q inversed_in $end
$var wire 1 ' rst $end
$var wire 3 R speed_in [2:0] $end
$var wire 1 S valid_in $end
$var wire 10 T vcount_in [9:0] $end
$var wire 1 : valid_out $end
$var wire 12 U pixel_out [11:0] $end
$var reg 1 V old_valid_in $end
$var reg 11 W x [10:0] $end
$var reg 10 X y [9:0] $end
$upscope $end
$scope module arrow3 $end
$var wire 1 $ clk $end
$var wire 2 Y direction_in [1:0] $end
$var wire 11 Z hcount_in [10:0] $end
$var wire 1 [ inversed_in $end
$var wire 1 ' rst $end
$var wire 3 \ speed_in [2:0] $end
$var wire 1 ] valid_in $end
$var wire 10 ^ vcount_in [9:0] $end
$var wire 1 9 valid_out $end
$var wire 12 _ pixel_out [11:0] $end
$var reg 1 ` old_valid_in $end
$var reg 11 a x [10:0] $end
$var reg 10 b y [9:0] $end
$upscope $end
$scope module frame_bottom $end
$var wire 11 c hcount_in [10:0] $end
$var wire 1 d is_fixed $end
$var wire 10 e vcount_in [9:0] $end
$var wire 11 f x_in [10:0] $end
$var wire 10 g y_in [9:0] $end
$var wire 12 h pixel_out [11:0] $end
$var wire 1 8 in_sprite $end
$var reg 1 8 in_sprite_buffer $end
$upscope $end
$scope module frame_left $end
$var wire 11 i hcount_in [10:0] $end
$var wire 1 j is_fixed $end
$var wire 10 k vcount_in [9:0] $end
$var wire 11 l x_in [10:0] $end
$var wire 10 m y_in [9:0] $end
$var wire 12 n pixel_out [11:0] $end
$var wire 1 6 in_sprite $end
$var reg 1 6 in_sprite_buffer $end
$upscope $end
$scope module frame_right $end
$var wire 11 o hcount_in [10:0] $end
$var wire 1 p is_fixed $end
$var wire 10 q vcount_in [9:0] $end
$var wire 11 r x_in [10:0] $end
$var wire 10 s y_in [9:0] $end
$var wire 12 t pixel_out [11:0] $end
$var wire 1 4 in_sprite $end
$var reg 1 4 in_sprite_buffer $end
$upscope $end
$scope module frame_top $end
$var wire 11 u hcount_in [10:0] $end
$var wire 1 v is_fixed $end
$var wire 10 w vcount_in [9:0] $end
$var wire 11 x x_in [10:0] $end
$var wire 10 y y_in [9:0] $end
$var wire 12 z pixel_out [11:0] $end
$var wire 1 2 in_sprite $end
$var reg 1 2 in_sprite_buffer $end
$upscope $end
$scope module player_shield $end
$var wire 11 { hcount_in [10:0] $end
$var wire 2 | rotate_in [1:0] $end
$var wire 10 } vcount_in [9:0] $end
$var wire 12 ~ pixel_out [11:0] $end
$var wire 1 !" in_sprite $end
$var reg 10 "" height [9:0] $end
$var reg 11 #" width [10:0] $end
$var reg 11 $" x [10:0] $end
$var reg 10 %" y [9:0] $end
$upscope $end
$upscope $end
$scope begin $ivl_for_loop0 $end
$var integer 32 &" i [31:0] $end
$upscope $end
$upscope $end
$enddefinitions $end
#0
$dumpvars
b0 &"
b101000000 %"
b111000000 $"
b10000000 #"
b100 ""
x!"
bx ~
bx }
b0 |
bx {
bx z
b0 y
b0 x
bx w
1v
bx u
bx t
b0 s
b0 r
bx q
1p
bx o
bx n
b0 m
b0 l
bx k
1j
bx i
bx h
b0 g
b0 f
bx e
1d
bx c
bx b
bx a
x`
bx00000000 _
bx ^
x]
b0 \
0[
bx Z
b10 Y
bx X
bx W
xV
bx00000000 U
bx T
xS
b0 R
0Q
bx P
b1 O
bx N
bx M
xL
bx00000000 K
bx J
xI
b0 H
0G
bx F
b0 E
bx D
bx C
bx B
xA
bx @
bx ?
bx00000000 >
bx00000000 =
bx00000000 <
x;
x:
x9
x8
bx 7
x6
bx 5
x4
bx 3
x2
bx 1
bx 0
bx /
bx .
bx -
bx ,
bx +
bx *
bx )
bx (
1'
bx &
bx %
0$
x#
x"
bx !
$end
#10000
b0 ?
b1010 B
b0 D
0"
0#
0A
1$
#20000
b0 7
b0 h
b0 5
b0 n
b0 3
b0 t
b0 1
b0 z
08
06
04
02
b111111111111 0
b111111111111 ~
0$
b0 &
b0 ,
b0 )
b0 .
b1000 (
b1000 -
b100000000 *
b100000000 /
b100000000 J
b100000000 T
b100000000 ^
b100000000 e
b100000000 k
b100000000 q
b100000000 w
b100000000 }
1!"
b1000000001 %
b1000000001 +
b1000000001 F
b1000000001 P
b1000000001 Z
b1000000001 c
b1000000001 i
b1000000001 o
b1000000001 u
b1000000001 {
0'
#30000
0I
0S
0]
b1000 B
b0 @
1#
1A
1$
#40000
0$
b1 &"
#50000
0L
0V
0`
b1 D
1$
#60000
0$
b10 &"
#70000
b10 D
1$
#80000
0$
b11 &"
#90000
b11 D
1$
#100000
0$
b100 &"
#110000
b100 D
1$
#120000
0$
b101 &"
#130000
b101 D
1$
#140000
0$
b110 &"
#150000
b110 D
1$
#160000
0$
b111 &"
#170000
b111 D
1$
#180000
0$
b1000 &"
#190000
b1000 D
1$
#200000
0$
b1001 &"
#210000
b1001 D
1$
#220000
0$
b1010 &"
#230000
b1010 D
1$
#240000
0$
b1011 &"
#250000
b1011 D
1$
#260000
0$
b1100 &"
#270000
b1100 D
1$
#280000
0$
b1101 &"
#290000
b1101 D
1$
#300000
0$
b1110 &"
#310000
b1110 D
1$
#320000
0$
b1111 &"
#330000
b1111 D
1$
#340000
0$
b10000 &"
#350000
b10000 D
1$
#360000
0$
b10001 &"
#370000
b10001 D
1$
#380000
0$
b10010 &"
#390000
b10010 D
1$
#400000
0$
b10011 &"
#410000
b10011 D
1$
#420000
0$
b10100 &"
#430000
b10100 D
1$
#440000
0$
b10101 &"
#450000
b10101 D
1$
#460000
0$
b10110 &"
#470000
b10110 D
1$
#480000
0$
b10111 &"
#490000
b10111 D
1$
#500000
0$
b11000 &"
#510000
b11000 D
1$
#520000
0$
b11001 &"
#530000
b11001 D
1$
#540000
0$
b11010 &"
#550000
b11010 D
1$
#560000
0$
b11011 &"
#570000
b11011 D
1$
#580000
0$
b11100 &"
#590000
b11100 D
1$
#600000
0$
b11101 &"
#610000
b11101 D
1$
#620000
0$
b11110 &"
#630000
b11110 D
1$
#640000
0$
b11111 &"
#650000
1I
b11 ?
b1 @
b0 D
1$
#660000
0$
b100000 &"
#670000
b111100000000 >
b111100000000 K
b1 D
1L
b0 N
1;
b1000000000 M
1$
#680000
0$
b100001 &"
#690000
b10 D
1$
#700000
0$
b100010 &"
#710000
b11 D
1$
#720000
0$
b100011 &"
#730000
b100 D
1$
#740000
0$
b100100 &"
#750000
b101 D
1$
#760000
0$
b100101 &"
#770000
b110 D
1$
#780000
0$
b100110 &"
#790000
b111 D
1$
#800000
0$
b100111 &"
#810000
b1000 D
1$
#820000
0$
b101000 &"
#830000
b1001 D
1$
#840000
0$
b101001 &"
#850000
b1010 D
1$
#860000
0$
b101010 &"
#870000
b1011 D
1$
#880000
0$
b101011 &"
#890000
b1100 D
1$
#900000
0$
b101100 &"
#910000
b1101 D
1$
#920000
0$
b101101 &"
#930000
b1110 D
1$
#940000
0$
b101110 &"
#950000
b1111 D
1$
#960000
0$
b101111 &"
#970000
b10000 D
1$
#980000
0$
b110000 &"
#990000
b10001 D
1$
#1000000
0$
b110001 &"
#1010000
b10010 D
1$
#1020000
0$
b110010 &"
#1030000
b10011 D
1$
#1040000
0$
b110011 &"
#1050000
b10100 D
1$
#1060000
0$
b110100 &"
#1070000
b10101 D
1$
#1080000
0$
b110101 &"
#1090000
b10110 D
1$
#1100000
0$
b110110 &"
#1110000
b10111 D
1$
#1120000
0$
b110111 &"
#1130000
b11000 D
1$
#1140000
0$
b111000 &"
#1150000
b11001 D
1$
#1160000
0$
b111001 &"
#1170000
b11010 D
1$
#1180000
0$
b111010 &"
#1190000
b11011 D
1$
#1200000
0$
b111011 &"
#1210000
b11100 D
1$
#1220000
0$
b111100 &"
#1230000
b11101 D
1$
#1240000
0$
b111101 &"
#1250000
b11110 D
1$
#1260000
0$
b111110 &"
#1270000
1S
b110 ?
b11 @
b0 D
1$
#1280000
0$
b111111 &"
#1290000
b111100000000 =
b111100000000 U
1V
b1011010000 X
1:
b1000000000 W
b1 D
1$
#1300000
0$
b1000000 &"
#1310000
b10 D
1$
#1320000
0$
b1000001 &"
#1330000
b11 D
1$
#1340000
0$
b1000010 &"
#1350000
b100 D
1$
#1360000
0$
b1000011 &"
#1370000
b101 D
1$
#1380000
0$
b1000100 &"
#1390000
b110 D
1$
#1400000
0$
b1000101 &"
#1410000
b111 D
1$
#1420000
0$
b1000110 &"
#1430000
b1000 D
1$
#1440000
0$
b1000111 &"
#1450000
b1001 D
1$
#1460000
0$
b1001000 &"
#1470000
b1010 D
1$
#1480000
0$
b1001001 &"
#1490000
b1011 D
1$
#1500000
0$
b1001010 &"
#1510000
b1100 D
1$
#1520000
0$
b1001011 &"
#1530000
b1101 D
1$
#1540000
0$
b1001100 &"
#1550000
b1110 D
1$
#1560000
0$
b1001101 &"
#1570000
b1111 D
1$
#1580000
0$
b1001110 &"
#1590000
b10000 D
1$
#1600000
0$
b1001111 &"
#1610000
b10001 D
1$
#1620000
0$
b1010000 &"
#1630000
b10010 D
1$
#1640000
0$
b1010001 &"
#1650000
b10011 D
1$
#1660000
0$
b1010010 &"
#1670000
b10100 D
1$
#1680000
0$
b1010011 &"
#1690000
b10101 D
1$
#1700000
0$
b1010100 &"
#1710000
b10110 D
1$
#1720000
0$
b1010101 &"
#1730000
b10111 D
1$
#1740000
0$
b1010110 &"
#1750000
b11000 D
1$
#1760000
0$
b1010111 &"
#1770000
b11001 D
1$
#1780000
0$
b1011000 &"
#1790000
b11010 D
1$
#1800000
0$
b1011001 &"
#1810000
b11011 D
1$
#1820000
0$
b1011010 &"
#1830000
b11100 D
1$
#1840000
0$
b1011011 &"
#1850000
b11101 D
1$
#1860000
0$
b1011100 &"
#1870000
b11110 D
1$
#1880000
0$
b1011101 &"
#1890000
1]
b1001 ?
b111 @
b0 D
1$
#1900000
0$
b1011110 &"
#1910000
b110100000000 !
b110100000000 C
b111100000000 <
b111100000000 _
b1 D
1`
b110000000 b
19
b0 a
1$
#1920000
0$
b1011111 &"
#1930000
b10 D
1$
#1940000
0$
b1100000 &"
#1950000
b11 D
1$
#1960000
0$
b1100001 &"
#1970000
b100 D
1$
#1980000
0$
b1100010 &"
#1990000
b101 D
1$
#2000000
0$
b1100011 &"
#2010000
b110 D
1$
#2020000
0$
b1100100 &"
#2030000
b111 D
1$
#2040000
0$
#2050000
b1000 D
1$
#2060000
0$
#2070000
b1001 D
1$
#2080000
0$
#2090000
b1010 D
1$
#2100000
0$
#2110000
b1011 D
1$
