src/block_sprite.sv
module block_sprite #(
  parameter WIDTH=256, HEIGHT=256,X_FIXED = 128,Y_FIXED = 128, COLOR=12'hFFF)(
  input wire is_fixed,
  input wire [10:0] x_in, hcount_in,
  input wire [9:0]  y_in, vcount_in,
  output logic [11:0] pixel_out,
  output logic in_sprite);

  logic in_sprite_buffer;
  always_comb begin
	  if(~is_fixed)begin
		  in_sprite_buffer = ((hcount_in >= x_in && hcount_in < (x_in + WIDTH)) && (vcount_in >= y_in && vcount_in < (y_in + HEIGHT)));
	  end else begin
		  in_sprite_buffer = ((hcount_in >= X_FIXED && hcount_in < (X_FIXED + WIDTH)) && (vcount_in >= Y_FIXED && vcount_in < (Y_FIXED + HEIGHT)));
	  end
  end


  assign pixel_out = in_sprite ? COLOR : 0;
  assign in_sprite = in_sprite_buffer;
endmodule

src/arrow.sv
`timescale 1ns / 1ps
`default_nettype none

module arrow #(parameter WIDTH = 8,HEIGHT = 32)(
	input wire clk,
	input wire[10:0] hcount_in,
	input wire[9:0] vcount_in,
	input wire valid_in,
	input wire[2:0] speed_in,
	input wire[1:0] direction_in,
	input wire inversed_in,

	output logic[11:0] pixel_out,
	output logic valid_out
);

logic[10:0] x;
logic[9:0] y;
logic old_valid_in;

always_ff @(posedge clk)begin
	if(~old_valid_in && valid_in)begin
		case(direction_in)
			2'b00:begin
				x <= 512;
				y <= 0;
			end
			2'b01:begin
				x <= 512;
				y <= 0;
			end
			2'b10:begin
				x <= 512;
				y <= 0;
			end
			2'b11:begin
				x <= 512;
				y <= 0;
			end
		endcase
	end else if(old_valid_in && valid_in)begin
		if(hcount_in == 0 && vcount_in == 0)begin
			case(direction_in)
                        	2'b00:begin
                                	y <= y + 4;
                        	end
                        	2'b01:begin
                                	y <= y + 4;
                        	end
                        	2'b10:begin
                                	y <= y + 4;
                        	end
                        	2'b11:begin
                                	y <= y + 4;
                        	end
			endcase


		end

	end
	old_valid_in <= valid_in;
end
assign valid_out = (hcount_in >= x) && (hcount_in <= x+WIDTH) && (vcount_in >= y) && (vcount_in <= y+HEIGHT);
assign pixel_out = valid_out ? 12'hF00 : 0;
endmodule
`default_nettype wire

src/shield.sv
`default_nettype none
`timescale 1ns / 1ps
module shield(
	input wire[10:0] hcount_in,
	input wire[9:0] vcount_in,
	input wire[1:0] rotate_in,

	output logic[11:0] pixel_out
);

logic[10:0] x,width;
logic[9:0] y,height;
always_comb begin
	case(rotate_in)
		2'b00:begin
			x = 448;
			y = 320;
			width = 128;
			height = 4;
		end
		2'b11:begin
			x = 448;
			y = 320;
			width = 4;
			height = 128;
		end
		2'b10:begin
			x = 568;
			y = 320;
			width = 4;
			height = 128;
		end
		2'b01:begin
			x = 448;
			y = 440;
			width = 128;
			height = 4;
		end
	endcase
end
logic in_sprite;
assign in_sprite = (hcount_in >= x) && (hcount_in <= x+width)  && ((vcount_in >= y) && (vcount_in <= y+height));
assign pixel_out = in_sprite ? 12'hFFF : 0;
endmodule
`default_nettype wire

src/enemy.sv
`default_nettype none
`timescale 1ns / 1ps

module enemy(
	input wire clk,
	input wire rst,
	input wire[10:0] hcount_in, //hcount
	input wire[9:0] vcount_in, //vcount
	input wire[3:0] state_in, //used to check if this module is busy
	input wire[3:0] turn_in, //to determine which pattern to adapt
	input wire[1:0] rotate_in, //input from camera interaction

	output logic busy_out, //busy while this is high
	output logic finished_out, //asserted high for one clk cycle when the module exits busy state
	output logic[11:0] pixel_out //pixel output
);
logic busy_out_buffer;

//shield
logic[11:0] shield_out;
shield player_shield(.hcount_in(hcount_in),.vcount_in(vcount_in),.rotate_in(2'b00),.pixel_out(shield_out));

logic[9:0] timings[71:0];
logic[9:0] speeds[71:0];
logic[9:0] directions[47:0];
logic[9:0] inverseds[23:0];
//patterns
//pattern #(72'h249_249_249_249_249_249,72'h249_249_249_249_249_249,48'h0,24'h0,0) pattern1(.turn_in(turn_in),.valid_out(1),.timing(timings[0]),.speed(speeds[0]),.direction(directions[0]),.inversed(inverseds[0]));

assign timings[0] = 72'h249_249_249_249_249_249;
//logic[23:0] arrow_on;
//24 arrows
logic[23:0] arrow_valid_in;
logic[23:0] arrow_out[11:0];
logic[23:0] arrow_valid_out;
arrow #(8,32) arrow1(.clk(clk),.hcount_in(hcount_in),.vcount_in(vcount_in),.valid_in(arrow_valid_in[0]),.speed_in(0),.direction_in(2'b00),.inversed_in(0),.pixel_out(arrow_out[0]),.valid_out(arrow_valid_out[0]));
arrow #(8,32) arrow2(.clk(clk),.hcount_in(hcount_in),.vcount_in(vcount_in),.valid_in(arrow_valid_in[1]),.speed_in(0),.direction_in(2'b01),.inversed_in(0),.pixel_out(arrow_out[1]),.valid_out(arrow_valid_out[1]));
arrow #(8,32) arrow3(.clk(clk),.hcount_in(hcount_in),.vcount_in(vcount_in),.valid_in(arrow_valid_in[2]),.speed_in(0),.direction_in(2'b10),.inversed_in(0),.pixel_out(arrow_out[2]),.valid_out(arrow_valid_out[2]));

logic frame_top_out,frame_bottom_out,frame_right_out,frame_left_out;
logic[11:0] frame_top_pixel;
logic[11:0] frame_bottom_pixel;
logic[11:0] frame_right_pixel;
logic[11:0] frame_left_pixel;
block_sprite #(160,8,432,304,12'hFFF) frame_top(.is_fixed(1),.x_in(0),.hcount_in(hcount_in),.y_in(0),.vcount_in(vcount_in),.pixel_out(frame_top_pixel),.in_sprite(frame_top_out));
block_sprite #(8,160,432,304,12'hFFF) frame_left(.is_fixed(1),.x_in(0),.hcount_in(hcount_in),.y_in(0),.vcount_in(vcount_in),.in_sprite(frame_left_out),.pixel_out(frame_left_pixel));
block_sprite #(8,160,584,304,12'hFFF) frame_right(.is_fixed(1),.x_in(0),.hcount_in(hcount_in),.y_in(0),.vcount_in(vcount_in),.in_sprite(frame_right_out),.pixel_out(frame_right_pixel));
block_sprite #(160,8,432,456,12'hFFF) frame_bottom(.is_fixed(1),.x_in(0),.hcount_in(hcount_in),.y_in(0),.vcount_in(vcount_in),.in_sprite(frame_bottom_out),.pixel_out(frame_bottom_pixel));

always_comb begin
	if(busy_out_buffer)begin
		/*if(frame_top_out)
                	pixel_out = frame_top_pixel;
        	if(frame_bottom_out)
                	pixel_out = frame_bottom_pixel;
        	if(frame_right_out)
                	pixel_out = frame_right_pixel;
        	if(frame_left_out)
                	pixel_out = frame_left_pixel;*/
		pixel_out = frame_bottom_pixel + frame_top_pixel + frame_left_pixel + frame_right_pixel + arrow_out[0] + arrow_out[1] + arrow_out[2];
	end
end


logic[31:0] timing_count;
logic[6:0] arrow_count_first;
logic[6:0] arrow_count_last;
logic[3:0] old_state_in; //detecting rising edge at the beginning of each phase
assign arrow_count_first = 0;
always_ff @(posedge clk)begin
	if(rst)begin
		busy_out_buffer <= 0;
		finished_out <= 0;
		timing_count <= 0;
		old_state_in <= 4'b1010;
		//pixel_out <= 0;
	end else begin
		if(state_in == 4'b1000 && old_state_in != state_in)begin
			busy_out_buffer <= 1;
			timing_count <= 0;
			//arrow_count_first <= 0;
			arrow_valid_in <= 24'h000001;
		end

			timing_count <= timing_count + 1;
                	if(timing_count == /*timings[0][arrow_count+:3]*/5*65000000/*timings[0][arrow_count_first+:3]*/)begin
                        	arrow_valid_in <= {arrow_valid_in[22:0],1'b1};
                       		timing_count <= 0;
                	end

		//end

		//end
		/*if(busy_out_buffer)begin
			if(hcount_in == 0 && vcount_in == 0)begin
				//arrow_valid_in <= 0;
				//arrow_valid_in = 24'h000003;
				timing_count <= timing_count + 1;
				if(timing_count == 10)begin
					timing_count <= 0;
					arrow_valid_in <= 24'h000003;
					//arrow_valid_in[1] <= 0;
				end
			end
		old_state_in <= state_in;
		end*/
	        old_state_in <= state_in;
	end
	//output the pixel value from 24 arrows, heart, etc. 
	//alpha blending
	//interval control
end

assign busy_out = busy_out_buffer;
endmodule
`default_nettype wire

sim/enemy_tb.sv
`default_nettype none
`timescale 1ns / 1ps

module enemy_tb;

logic clk;
logic rst;

logic [10:0] hcount_in;
logic [9:0] vcount_in;
logic [3:0] state_in;
logic [3:0] turn_in;
logic [1:0] rotate_in;

logic busy_out;
logic finished_out;
logic [11:0] pixel_out;
enemy uut(
	.clk(clk),
	.rst(rst),
	.hcount_in(hcount_in),
	.vcount_in(vcount_in),
	.state_in(state_in),
	.turn_in(turn_in),
	.rotate_in(rotate_in),
	.busy_out(busy_out),
	.finished_out(finished_out),
	.pixel_out(pixel_out)
);

always begin
	#10;
       	clk = !clk;
end

initial begin
	$display("Starting Sim");
	$dumpfile("enemy.vcd");
	$dumpvars(0,enemy_tb);
	rst = 1;
	clk = 0;
	#20;
	rst = 0;
	for(int i = 0;i<30;i++)begin
		hcount_in = 0;
		vcount_in = 0;
		state_in = 4'b1000;
		turn_in = 0;
		rotate_in = 2'b0;
		#20;
	end
	#100;
	$display("Finishing Sim");
	$finish;
end


endmodule
`default_nettype wire

enemy.vcd
$date
	Mon Nov 14 18:57:21 2022
$end
$version
	Icarus Verilog
$end
$timescale
	1ps
$end
$scope module enemy_tb $end
$var wire 12 ! pixel_out [11:0] $end
$var wire 1 " finished_out $end
$var wire 1 # busy_out $end
$var reg 1 $ clk $end
$var reg 11 % hcount_in [10:0] $end
$var reg 2 & rotate_in [1:0] $end
$var reg 1 ' rst $end
$var reg 4 ( state_in [3:0] $end
$var reg 4 ) turn_in [3:0] $end
$var reg 10 * vcount_in [9:0] $end
$scope module uut $end
$var wire 7 + arrow_count_first [6:0] $end
$var wire 1 # busy_out $end
$var wire 1 $ clk $end
$var wire 11 , hcount_in [10:0] $end
$var wire 2 - rotate_in [1:0] $end
$var wire 1 ' rst $end
$var wire 4 . state_in [3:0] $end
$var wire 4 / turn_in [3:0] $end
$var wire 10 0 vcount_in [9:0] $end
$var wire 12 1 shield_out [11:0] $end
$var wire 12 2 frame_top_pixel [11:0] $end
$var wire 1 3 frame_top_out $end
$var wire 12 4 frame_right_pixel [11:0] $end
$var wire 1 5 frame_right_out $end
$var wire 12 6 frame_left_pixel [11:0] $end
$var wire 1 7 frame_left_out $end
$var wire 12 8 frame_bottom_pixel [11:0] $end
$var wire 1 9 frame_bottom_out $end
$var wire 24 : arrow_valid_out [23:0] $end
$var reg 24 ; arrow_valid_in [23:0] $end
$var reg 1 < busy_out_buffer $end
$var reg 1 " finished_out $end
$var reg 4 = old_state_in [3:0] $end
$var reg 12 > pixel_out [11:0] $end
$var reg 32 ? timing_count [31:0] $end
$scope module arrow1 $end
$var wire 1 $ clk $end
$var wire 2 @ direction_in [1:0] $end
$var wire 11 A hcount_in [10:0] $end
$var wire 1 B inversed_in $end
$var wire 3 C speed_in [2:0] $end
$var wire 1 D valid_in $end
$var wire 1 E valid_out $end
$var wire 10 F vcount_in [9:0] $end
$var wire 12 G pixel_out [11:0] $end
$var reg 1 H old_valid_in $end
$var reg 11 I x [10:0] $end
$var reg 10 J y [9:0] $end
$upscope $end
$scope module arrow2 $end
$var wire 1 $ clk $end
$var wire 2 K direction_in [1:0] $end
$var wire 11 L hcount_in [10:0] $end
$var wire 1 M inversed_in $end
$var wire 3 N speed_in [2:0] $end
$var wire 1 O valid_in $end
$var wire 1 P valid_out $end
$var wire 10 Q vcount_in [9:0] $end
$var wire 12 R pixel_out [11:0] $end
$var reg 1 S old_valid_in $end
$var reg 11 T x [10:0] $end
$var reg 10 U y [9:0] $end
$upscope $end
$scope module arrow3 $end
$var wire 1 $ clk $end
$var wire 2 V direction_in [1:0] $end
$var wire 11 W hcount_in [10:0] $end
$var wire 1 X inversed_in $end
$var wire 3 Y speed_in [2:0] $end
$var wire 1 Z valid_in $end
$var wire 1 [ valid_out $end
$var wire 10 \ vcount_in [9:0] $end
$var wire 12 ] pixel_out [11:0] $end
$var reg 1 ^ old_valid_in $end
$var reg 11 _ x [10:0] $end
$var reg 10 ` y [9:0] $end
$upscope $end
$scope module frame_bottom $end
$var wire 11 a hcount_in [10:0] $end
$var wire 1 b is_fixed $end
$var wire 10 c vcount_in [9:0] $end
$var wire 11 d x_in [10:0] $end
$var wire 10 e y_in [9:0] $end
$var wire 12 f pixel_out [11:0] $end
$var wire 1 9 in_sprite $end
$var reg 1 9 in_sprite_buffer $end
$upscope $end
$scope module frame_left $end
$var wire 11 g hcount_in [10:0] $end
$var wire 1 h is_fixed $end
$var wire 10 i vcount_in [9:0] $end
$var wire 11 j x_in [10:0] $end
$var wire 10 k y_in [9:0] $end
$var wire 12 l pixel_out [11:0] $end
$var wire 1 7 in_sprite $end
$var reg 1 7 in_sprite_buffer $end
$upscope $end
$scope module frame_right $end
$var wire 11 m hcount_in [10:0] $end
$var wire 1 n is_fixed $end
$var wire 10 o vcount_in [9:0] $end
$var wire 11 p x_in [10:0] $end
$var wire 10 q y_in [9:0] $end
$var wire 12 r pixel_out [11:0] $end
$var wire 1 5 in_sprite $end
$var reg 1 5 in_sprite_buffer $end
$upscope $end
$scope module frame_top $end
$var wire 11 s hcount_in [10:0] $end
$var wire 1 t is_fixed $end
$var wire 10 u vcount_in [9:0] $end
$var wire 11 v x_in [10:0] $end
$var wire 10 w y_in [9:0] $end
$var wire 12 x pixel_out [11:0] $end
$var wire 1 3 in_sprite $end
$var reg 1 3 in_sprite_buffer $end
$upscope $end
$scope module player_shield $end
$var wire 11 y hcount_in [10:0] $end
$var wire 2 z rotate_in [1:0] $end
$var wire 10 { vcount_in [9:0] $end
$var wire 12 | pixel_out [11:0] $end
$var wire 1 } in_sprite $end
$var reg 10 ~ height [9:0] $end
$var reg 11 !" width [10:0] $end
$var reg 11 "" x [10:0] $end
$var reg 10 #" y [9:0] $end
$upscope $end
$upscope $end
$scope begin $ivl_for_loop0 $end
$var integer 32 $" i [31:0] $end
$upscope $end
$upscope $end
$enddefinitions $end
#0
$dumpvars
b0 $"
b101000000 #"
b111000000 ""
b10000000 !"
b100 ~
x}
bx |
bx {
b0 z
bx y
bx x
b0 w
b0 v
bx u
1t
bx s
bx r
b0 q
b0 p
bx o
1n
bx m
bx l
b0 k
b0 j
bx i
1h
bx g
bx f
b0 e
b0 d
bx c
1b
bx a
bx `
bx _
x^
bx00000000 ]
bx \
x[
xZ
b0 Y
0X
bx W
b10 V
bx U
bx T
xS
bx00000000 R
bx Q
xP
xO
b0 N
0M
bx L
b1 K
bx J
bx I
xH
bx00000000 G
bx F
xE
xD
b0 C
0B
bx A
b0 @
bx ?
bx >
bx =
x<
bx ;
bzxxx :
x9
bx 8
x7
bx 6
x5
bx 4
x3
bx 2
bx 1
bx 0
bx /
bx .
bx -
bx ,
b0 +
bx *
bx )
bx (
1'
bx &
bx %
0$
x#
x"
bx !
$end
#10000
b1010 =
b0 ?
0"
0#
0<
1$
#20000
b0 8
b0 f
b0 6
b0 l
b0 4
b0 r
b0 2
b0 x
09
07
05
03
b0 1
b0 |
0$
b0 &
b0 -
b0 )
b0 /
b1000 (
b1000 .
b0 *
b0 0
b0 F
b0 Q
b0 \
b0 c
b0 i
b0 o
b0 u
b0 {
0}
b0 %
b0 ,
b0 A
b0 L
b0 W
b0 a
b0 g
b0 m
b0 s
b0 y
0'
#30000
1D
0O
0Z
b1000 =
b1 ?
b1 ;
1#
1<
1$
#40000
0$
b1 $"
#50000
1H
0S
0^
b10 ?
1$
#60000
0$
b10 $"
#70000
b11 ?
1$
#80000
0$
b11 $"
#90000
b100 ?
1$
#100000
0$
b100 $"
#110000
b101 ?
1$
#120000
0$
b101 $"
#130000
b110 ?
1$
#140000
0$
b110 $"
#150000
b111 ?
1$
#160000
0$
b111 $"
#170000
b1000 ?
1$
#180000
0$
b1000 $"
#190000
b1001 ?
1$
#200000
0$
b1001 $"
#210000
b1010 ?
1$
#220000
0$
b1010 $"
#230000
b1011 ?
1$
#240000
0$
b1011 $"
#250000
b1100 ?
1$
#260000
0$
b1100 $"
#270000
b1101 ?
1$
#280000
0$
b1101 $"
#290000
b1110 ?
1$
#300000
0$
b1110 $"
#310000
b1111 ?
1$
#320000
0$
b1111 $"
#330000
b10000 ?
1$
#340000
0$
b10000 $"
#350000
b10001 ?
1$
#360000
0$
b10001 $"
#370000
b10010 ?
1$
#380000
0$
b10010 $"
#390000
b10011 ?
1$
#400000
0$
b10011 $"
#410000
b10100 ?
1$
#420000
0$
b10100 $"
#430000
b10101 ?
1$
#440000
0$
b10101 $"
#450000
b10110 ?
1$
#460000
0$
b10110 $"
#470000
b10111 ?
1$
#480000
0$
b10111 $"
#490000
b11000 ?
1$
#500000
0$
b11000 $"
#510000
b11001 ?
1$
#520000
0$
b11001 $"
#530000
b11010 ?
1$
#540000
0$
b11010 $"
#550000
b11011 ?
1$
#560000
0$
b11011 $"
#570000
b11100 ?
1$
#580000
0$
b11100 $"
#590000
b11101 ?
1$
#600000
0$
b11101 $"
#610000
b11110 ?
1$
#620000
0$
b11110 $"
#630000
b11111 ?
1$
#640000
0$
#650000
b100000 ?
1$
#660000
0$
#670000
b100001 ?
1$
#680000
0$
#690000
b100010 ?
1$
#700000
0$
#710000
b100011 ?
1$
