src/block_sprite.sv
module block_sprite #(
  parameter WIDTH=256, HEIGHT=256,X_FIXED = 128,Y_FIXED = 128, COLOR=12'hFFF)(
  input wire is_fixed,
  input wire [10:0] x_in, hcount_in,
  input wire [9:0]  y_in, vcount_in,
  output logic [11:0] pixel_out,
  output logic in_sprite);

  logic in_sprite_buffer;
  always_comb begin
	  if(~is_fixed)begin
		  in_sprite_buffer = ((hcount_in >= x_in && hcount_in < (x_in + WIDTH)) && (vcount_in >= y_in && vcount_in < (y_in + HEIGHT)));
	  end else begin
		  in_sprite_buffer = ((hcount_in >= X_FIXED && hcount_in < (X_FIXED + WIDTH)) && (vcount_in >= Y_FIXED && vcount_in < (Y_FIXED + HEIGHT)));
	  end
  end


  assign pixel_out = in_sprite ? COLOR : 0;
  assign in_sprite = in_sprite_buffer;
endmodule

src/menu.sv
`default_nettype none
`timescale 1ns / 1ps
module menu(
	input wire clk,
	input wire rst,
	input wire[10:0] hcount_in,
	input wire[9:0] vcount_in,
	input wire[3:0] state_in,

	output logic busy_out,
	output logic finished_out,
	output logic[11:0] pixel_out
);

logic frame_top_out,frame_bottom_out,frame_right_out,frame_left_out;
logic[11:0] frame_top_pixel;
logic[11:0] frame_bottom_pixel;
logic[11:0] frame_right_pixel;
logic[11:0] frame_left_pixel;
block_sprite #(768,8,128,384,12'hFFF) frame_top(.is_fixed(1),.x_in(0),.hcount_in(hcount_in),.y_in(0),.vcount_in(vcount_in),.pixel_out(frame_top_pixel),.in_sprite(frame_top_out));
block_sprite #(8,192,128,384,12'hFFF) frame_left(.is_fixed(1),.x_in(0),.hcount_in(hcount_in),.y_in(0),.vcount_in(vcount_in),.in_sprite(frame_left_out),.pixel_out(frame_left_pixel));
block_sprite #(8,192,888,384,12'hFFF) frame_right(.is_fixed(1),.x_in(0),.hcount_in(hcount_in),.y_in(0),.vcount_in(vcount_in),.in_sprite(frame_right_out),.pixel_out(frame_right_pixel));
block_sprite #(768,8,128,568,12'hFFF) frame_bottom(.is_fixed(1),.x_in(0),.hcount_in(hcount_in),.y_in(0),.vcount_in(vcount_in),.in_sprite(frame_bottom_out),.pixel_out(frame_bottom_pixel));

logic busy_out_buffer;
logic[3:0] old_state_in;
logic[31:0] timing_count;
always_comb begin
	if(busy_out_buffer == 1)begin
		pixel_out = frame_bottom_pixel + frame_top_pixel + frame_left_pixel + frame_right_pixel;
	end
	else
		pixel_out = frame_bottom_pixel;
end
always_ff @(posedge clk)begin
	if(rst)begin
		finished_out <= 0;
		busy_out_buffer <= 0;
		old_state_in = 4'b1010;
	end
	else begin
		if(old_state_in != state_in && state_in == 4'b0000)begin
			busy_out_buffer <= 1;
			timing_count <= 0;
		end
		if(busy_out_buffer == 1)begin
			timing_count <= timing_count + 1;
			if(timing_count == 5*6500000)begin
				timing_count <= 0;
				finished_out <= 1;
				busy_out_buffer <= 0;
				//old_state_in = 4'b1010;
			end
			//old_state_in <= state_in;
		end
		if(finished_out == 1)begin
			finished_out <= 0;
		end
		old_state_in <= state_in;
	end
end
assign busy_out = busy_out_buffer;
//assign finished_out = 0;
endmodule
`default_nettype wire

sim/menu_tb.sv
`default_nettype none
`timescale 1ns / 1ps
module menu_tb;

logic clk;
logic rst;

logic[10:0] hcount_in;
logic[9:0] vcount_in;
logic[1:0] state_in;

logic busy_out;
logic finished_out;
logic[11:0] pixel_out;

menu uut(
	.clk(clk),
	.rst(rst),
	.hcount_in(hcount_in),
	.vcount_in(vcount_in),
	.state_in(state_in),
	.busy_out(busy_out),
	.finished_out(finished_out),
	.pixel_out(pixel_out)
);

always begin
        #10;
        clk = !clk;
end
initial begin
	$display("Starting Sim");
        $dumpfile("menu.vcd");
        $dumpvars(0,menu_tb);

	rst = 1;
	clk = 0;
	#20;
	rst = 0;
	for(int i = 0;i<100;i++)begin
		hcount_in = 0;
		vcount_in = 0;
		state_in = 4'b0000;
		#20;
	end

	$display("Finishing Sim");
        $finish;

end


endmodule
`default_nettype wire

menu.vcd
$date
	Thu Nov 17 10:01:15 2022
$end
$version
	Icarus Verilog
$end
$timescale
	1ps
$end
$scope module menu_tb $end
$var wire 12 ! pixel_out [11:0] $end
$var wire 1 " finished_out $end
$var wire 1 # busy_out $end
$var reg 1 $ clk $end
$var reg 11 % hcount_in [10:0] $end
$var reg 1 & rst $end
$var reg 2 ' state_in [1:0] $end
$var reg 10 ( vcount_in [9:0] $end
$scope module uut $end
$var wire 1 # busy_out $end
$var wire 1 $ clk $end
$var wire 11 ) hcount_in [10:0] $end
$var wire 1 & rst $end
$var wire 4 * state_in [3:0] $end
$var wire 10 + vcount_in [9:0] $end
$var wire 12 , frame_top_pixel [11:0] $end
$var wire 1 - frame_top_out $end
$var wire 12 . frame_right_pixel [11:0] $end
$var wire 1 / frame_right_out $end
$var wire 12 0 frame_left_pixel [11:0] $end
$var wire 1 1 frame_left_out $end
$var wire 12 2 frame_bottom_pixel [11:0] $end
$var wire 1 3 frame_bottom_out $end
$var reg 1 4 busy_out_buffer $end
$var reg 1 " finished_out $end
$var reg 4 5 old_state_in [3:0] $end
$var reg 12 6 pixel_out [11:0] $end
$var reg 32 7 timing_count [31:0] $end
$scope module frame_bottom $end
$var wire 11 8 hcount_in [10:0] $end
$var wire 1 9 is_fixed $end
$var wire 10 : vcount_in [9:0] $end
$var wire 11 ; x_in [10:0] $end
$var wire 10 < y_in [9:0] $end
$var wire 12 = pixel_out [11:0] $end
$var wire 1 3 in_sprite $end
$var reg 1 3 in_sprite_buffer $end
$upscope $end
$scope module frame_left $end
$var wire 11 > hcount_in [10:0] $end
$var wire 1 ? is_fixed $end
$var wire 10 @ vcount_in [9:0] $end
$var wire 11 A x_in [10:0] $end
$var wire 10 B y_in [9:0] $end
$var wire 12 C pixel_out [11:0] $end
$var wire 1 1 in_sprite $end
$var reg 1 1 in_sprite_buffer $end
$upscope $end
$scope module frame_right $end
$var wire 11 D hcount_in [10:0] $end
$var wire 1 E is_fixed $end
$var wire 10 F vcount_in [9:0] $end
$var wire 11 G x_in [10:0] $end
$var wire 10 H y_in [9:0] $end
$var wire 12 I pixel_out [11:0] $end
$var wire 1 / in_sprite $end
$var reg 1 / in_sprite_buffer $end
$upscope $end
$scope module frame_top $end
$var wire 11 J hcount_in [10:0] $end
$var wire 1 K is_fixed $end
$var wire 10 L vcount_in [9:0] $end
$var wire 11 M x_in [10:0] $end
$var wire 10 N y_in [9:0] $end
$var wire 12 O pixel_out [11:0] $end
$var wire 1 - in_sprite $end
$var reg 1 - in_sprite_buffer $end
$upscope $end
$upscope $end
$scope begin $ivl_for_loop0 $end
$var integer 32 P i [31:0] $end
$upscope $end
$upscope $end
$enddefinitions $end
#0
$dumpvars
b0 P
bx O
b0 N
b0 M
bx L
1K
bx J
bx I
b0 H
b0 G
bx F
1E
bx D
bx C
b0 B
b0 A
bx @
1?
bx >
bx =
b0 <
b0 ;
bx :
19
bx 8
bx 7
bx 6
bx 5
x4
x3
bx 2
x1
bx 0
x/
bx .
x-
bx ,
bx +
b0xx *
bx )
bx (
bx '
1&
bx %
0$
x#
x"
bx !
$end
#10000
0#
04
0"
b1010 5
1$
#20000
b0 2
b0 =
b0 0
b0 C
b0 .
b0 I
b0 ,
b0 O
03
01
0/
0-
0$
b0 *
b0 '
b0 (
b0 +
b0 :
b0 @
b0 F
b0 L
b0 %
b0 )
b0 8
b0 >
b0 D
b0 J
0&
#30000
b0 !
b0 6
b0 5
b0 7
1#
14
1$
#40000
0$
b1 P
#50000
b1 7
1$
#60000
0$
b10 P
#70000
b10 7
1$
#80000
0$
b11 P
#90000
b11 7
1$
#100000
0$
b100 P
#110000
b100 7
1$
#120000
0$
b101 P
#130000
b101 7
1$
#140000
0$
b110 P
#150000
b110 7
1$
#160000
0$
b111 P
#170000
b111 7
1$
#180000
0$
b1000 P
#190000
b1000 7
1$
#200000
0$
b1001 P
#210000
b1001 7
1$
#220000
0$
b1010 P
#230000
b1010 7
1$
#240000
0$
b1011 P
#250000
b1011 7
1$
#260000
0$
b1100 P
#270000
b1100 7
1$
#280000
0$
b1101 P
#290000
b1101 7
1$
#300000
0$
b1110 P
#310000
b1110 7
1$
#320000
0$
b1111 P
#330000
b1111 7
1$
#340000
0$
b10000 P
#350000
b10000 7
1$
#360000
0$
b10001 P
#370000
b10001 7
1$
#380000
0$
b10010 P
#390000
b10010 7
1$
#400000
0$
b10011 P
#410000
b10011 7
1$
#420000
0$
b10100 P
#430000
b10100 7
1$
#440000
0$
b10101 P
#450000
b10101 7
1$
#460000
0$
b10110 P
#470000
b10110 7
1$
#480000
0$
b10111 P
#490000
b10111 7
1$
#500000
0$
b11000 P
#510000
b11000 7
1$
#520000
0$
b11001 P
#530000
b11001 7
1$
#540000
0$
b11010 P
#550000
b11010 7
1$
#560000
0$
b11011 P
#570000
b11011 7
1$
#580000
0$
b11100 P
#590000
b11100 7
1$
#600000
0$
b11101 P
#610000
b11101 7
1$
#620000
0$
b11110 P
#630000
b11110 7
1$
#640000
0$
b11111 P
#650000
0#
04
1"
b0 7
1$
#660000
0$
b100000 P
#670000
0"
1$
#680000
0$
b100001 P
#690000
1$
#700000
0$
b100010 P
#710000
1$
#720000
0$
b100011 P
#730000
1$
#740000
0$
b100100 P
#750000
1$
#760000
0$
b100101 P
#770000
1$
#780000
0$
b100110 P
#790000
1$
#800000
0$
b100111 P
#810000
1$
#820000
0$
b101000 P
#830000
1$
#840000
0$
b101001 P
#850000
1$
#860000
0$
b101010 P
#870000
1$
#880000
0$
b101011 P
#890000
1$
#900000
0$
b101100 P
#910000
1$
#920000
0$
b101101 P
#930000
1$
#940000
0$
b101110 P
#950000
1$
#960000
0$
b101111 P
#970000
1$
#980000
0$
b110000 P
#990000
1$
#1000000
0$
b110001 P
#1010000
1$
#1020000
0$
b110010 P
#1030000
1$
#1040000
0$
b110011 P
#1050000
1$
#1060000
0$
b110100 P
#1070000
1$
#1080000
0$
b110101 P
#1090000
1$
#1100000
0$
b110110 P
#1110000
1$
#1120000
0$
b110111 P
#1130000
1$
#1140000
0$
b111000 P
#1150000
1$
#1160000
0$
b111001 P
#1170000
1$
#1180000
0$
b111010 P
#1190000
1$
#1200000
0$
b111011 P
#1210000
1$
#1220000
0$
b111100 P
#1230000
1$
#1240000
0$
b111101 P
#1250000
1$
#1260000
0$
b111110 P
#1270000
1$
#1280000
0$
b111111 P
#1290000
1$
#1300000
0$
b1000000 P
#1310000
1$
#1320000
0$
b1000001 P
#1330000
1$
#1340000
0$
b1000010 P
#1350000
1$
#1360000
0$
b1000011 P
#1370000
1$
#1380000
0$
b1000100 P
#1390000
1$
#1400000
0$
b1000101 P
#1410000
1$
#1420000
0$
b1000110 P
#1430000
1$
#1440000
0$
b1000111 P
#1450000
1$
#1460000
0$
b1001000 P
#1470000
1$
#1480000
0$
b1001001 P
#1490000
1$
#1500000
0$
b1001010 P
#1510000
1$
#1520000
0$
b1001011 P
#1530000
1$
#1540000
0$
b1001100 P
#1550000
1$
#1560000
0$
b1001101 P
#1570000
1$
#1580000
0$
b1001110 P
#1590000
1$
#1600000
0$
b1001111 P
#1610000
1$
#1620000
0$
b1010000 P
#1630000
1$
#1640000
0$
b1010001 P
#1650000
1$
#1660000
0$
b1010010 P
#1670000
1$
#1680000
0$
b1010011 P
#1690000
1$
#1700000
0$
b1010100 P
#1710000
1$
#1720000
0$
b1010101 P
#1730000
1$
#1740000
0$
b1010110 P
#1750000
1$
#1760000
0$
b1010111 P
#1770000
1$
#1780000
0$
b1011000 P
#1790000
1$
#1800000
0$
b1011001 P
#1810000
1$
#1820000
0$
b1011010 P
#1830000
1$
#1840000
0$
b1011011 P
#1850000
1$
#1860000
0$
b1011100 P
#1870000
1$
#1880000
0$
b1011101 P
#1890000
1$
#1900000
0$
b1011110 P
#1910000
1$
#1920000
0$
b1011111 P
#1930000
1$
#1940000
0$
b1100000 P
#1950000
1$
#1960000
0$
b1100001 P
#1970000
1$
#1980000
0$
b1100010 P
#1990000
1$
#2000000
0$
b1100011 P
#2010000
1$
#2020000
0$
b1100100 P
