src/shield.sv
`default_nettype none
`timescale 1ns / 1ps
module shield(
	input wire[10:0] hcount_in,
	input wire[9:0] vcount_in,
	input wire[1:0] rotate_in,

	output logic[11:0] pixel_out
);

logic[10:0] x,width;
logic[9:0] y,height;
always_comb begin
	case(rotate_in)
		2'b00:begin
			x = 448;
			y = 320;
			width = 128;
			height = 4;
		end
		2'b11:begin
			x = 448;
			y = 320;
			width = 4;
			height = 128;
		end
		2'b10:begin
			x = 568;
			y = 320;
			width = 4;
			height = 128;
		end
		2'b01:begin
			x = 448;
			y = 440;
			width = 128;
			height = 4;
		end
	endcase
end
logic in_sprite;
assign in_sprite = (hcount_in >= x) && (hcount_in <= x+width)  && ((vcount_in >= y) && (vcount_in <= y+height));
assign pixel_out = in_sprite ? 12'hFFF : 0;
endmodule
`default_nettype wire

sim/shield_tb.sv
`default_nettype none
`timescale 1ns / 1ps

module shield_tb;
logic[10:0] hcount_in;
logic[9:0] vcount_in;
logic[1:0] rotate_in;

logic[11:0] pixel_out;

shield uut(
	.hcount_in(hcount_in),
	.vcount_in(vcount_in),
	.rotate_in(rotate_in),
	.pixel_out(pixel_out)
);

initial begin
	$display("Starting Sim");
        $dumpfile("shield.vcd");
        $dumpvars(0,shield_tb);

	for(int i = 0;i < 100;i++)begin
		hcount_in = 0;
		vcount_in = 0;
		rotate_in = 2'b00;
		#20;
	end
	$display("Finishing Sim");
        $finish;


end


endmodule
`default_nettype wire

shield.vcd
$date
	Tue Nov 15 19:53:08 2022
$end
$version
	Icarus Verilog
$end
$timescale
	1ps
$end
$scope module shield_tb $end
$var wire 12 ! pixel_out [11:0] $end
$var reg 11 " hcount_in [10:0] $end
$var reg 2 # rotate_in [1:0] $end
$var reg 10 $ vcount_in [9:0] $end
$scope module uut $end
$var wire 11 % hcount_in [10:0] $end
$var wire 1 & in_sprite $end
$var wire 2 ' rotate_in [1:0] $end
$var wire 10 ( vcount_in [9:0] $end
$var wire 12 ) pixel_out [11:0] $end
$var reg 10 * height [9:0] $end
$var reg 11 + width [10:0] $end
$var reg 11 , x [10:0] $end
$var reg 10 - y [9:0] $end
$upscope $end
$scope begin $ivl_for_loop0 $end
$var integer 32 . i [31:0] $end
$upscope $end
$upscope $end
$enddefinitions $end
#0
$dumpvars
b0 .
b101000000 -
b111000000 ,
b10000000 +
b100 *
b0 )
b0 (
b0 '
0&
b0 %
b0 $
b0 #
b0 "
b0 !
$end
#20000
b1 .
#40000
b10 .
#60000
b11 .
#80000
b100 .
#100000
b101 .
#120000
b110 .
#140000
b111 .
#160000
b1000 .
#180000
b1001 .
#200000
b1010 .
#220000
b1011 .
#240000
b1100 .
#260000
b1101 .
#280000
b1110 .
#300000
b1111 .
#320000
b10000 .
#340000
b10001 .
#360000
b10010 .
#380000
b10011 .
#400000
b10100 .
#420000
b10101 .
#440000
b10110 .
#460000
b10111 .
#480000
b11000 .
#500000
b11001 .
#520000
b11010 .
#540000
b11011 .
#560000
b11100 .
#580000
b11101 .
#600000
b11110 .
#620000
b11111 .
#640000
b100000 .
#660000
b100001 .
#680000
b100010 .
#700000
b100011 .
#720000
b100100 .
#740000
b100101 .
#760000
b100110 .
#780000
b100111 .
#800000
b101000 .
#820000
b101001 .
#840000
b101010 .
#860000
b101011 .
#880000
b101100 .
#900000
b101101 .
#920000
b101110 .
#940000
b101111 .
#960000
b110000 .
#980000
b110001 .
#1000000
b110010 .
#1020000
b110011 .
#1040000
b110100 .
#1060000
b110101 .
#1080000
b110110 .
#1100000
b110111 .
#1120000
b111000 .
#1140000
b111001 .
#1160000
b111010 .
#1180000
b111011 .
#1200000
b111100 .
#1220000
b111101 .
#1240000
b111110 .
#1260000
b111111 .
#1280000
b1000000 .
#1300000
b1000001 .
#1320000
b1000010 .
#1340000
b1000011 .
#1360000
b1000100 .
#1380000
b1000101 .
#1400000
b1000110 .
#1420000
b1000111 .
#1440000
b1001000 .
#1460000
b1001001 .
#1480000
b1001010 .
#1500000
b1001011 .
#1520000
b1001100 .
#1540000
b1001101 .
#1560000
b1001110 .
#1580000
b1001111 .
#1600000
b1010000 .
#1620000
b1010001 .
#1640000
b1010010 .
#1660000
b1010011 .
#1680000
b1010100 .
#1700000
b1010101 .
#1720000
b1010110 .
#1740000
b1010111 .
#1760000
b1011000 .
#1780000
b1011001 .
#1800000
b1011010 .
#1820000
b1011011 .
#1840000
b1011100 .
#1860000
b1011101 .
#1880000
b1011110 .
#1900000
b1011111 .
#1920000
b1100000 .
#1940000
b1100001 .
#1960000
b1100010 .
#1980000
b1100011 .
#2000000
b1100100 .
